dirlock/__init__.py
dirlock-0.3.dist-info/METADATA
dirlock-0.3.dist-info/WHEEL
dirlock-0.3.dist-info/top_level.txt
dirlock-0.3.dist-info/RECORD
