Metadata-Version: 2.4
Name: dirlock
Version: 0.3
Summary: A simple directory based lock implementation for Python.
Home-page: https://github.com/z3rone-org/dirlock
Author: Falk B. Schimweg
Author-email: git@falk.schimweg.de
License: MIT
Classifier: Programming Language :: Python :: 3
Classifier: License :: OSI Approved :: MIT License
Classifier: Operating System :: OS Independent
Requires-Python: >=3.8
Provides-Extra: dev
Requires-Dist: pytest; extra == "dev"
Dynamic: author
Dynamic: author-email
Dynamic: classifier
Dynamic: description
Dynamic: description-content-type
Dynamic: home-page
Dynamic: license
Dynamic: provides-extra
Dynamic: requires-python
Dynamic: summary
